<?xml version="1.0" encoding="utf-8"?>
<resources>

    <!-- iOS specific untranslated strings -->
    <string name="email">Email</string>
    <string name="contact_nickname">new contacts nickname</string>
    <string name="imap_password">your IMAP password</string>
    <string name="success">Success</string>
    <string name="videos">Videos</string>
    <string name="hide">Hide</string>
    <string name="login_error_title">Unable to login!</string>
    <string name="start_chat">Start Chat</string>
    <string name="dismiss">Dismiss</string>
    <string name="photo">Photo</string>
    <string name="search_contact">Search Contact</string>
    <string name="import_contacts">Import Device Contacts</string>
    <string name="import_contacts_message">To chat with contacts from your device open the settings menu and enable the Contacts option</string>
    <string name="synchronizing_account">Synchronizing Account</string>
    <string name="invalid_qr_code">Invalid group QR Code</string>
    <string name="open_settings">Open Settings</string>
    <string name="my_profile">My Profile</string>
    <string name="no_account_setup">No Account set up</string>
    <string name="create_backup">Create backup</string>
    <string name="delete_account">Delete Account</string>
    <string name="delete_account_message">Are you sure you wante to delete your account data?</string>
    <string name="display_name">Display Name</string>
    <string name="status">Status</string>
    <string name="configure_my_account">Configure my Account</string>
    <string name="save_mime_headers">Save Mime Headers</string>
    <string name="flags">Flags</string>
    <string name="user_details">User Details</string>
    <string name="danger">Danger</string>
    <string name="creating_backup">Creating Backup</string>
    <string name="group_info">Group Info</string>
    <string name="next">Next</string>
    <string name="reset">Reset</string>
    <string name="your_status">Your Status</string>
    <string name="edit_contact">Edit contact</string>
    <string name="custom_port">Custom Port</string>
    <string name="automatic">Automatic</string>
    <string name="complete">Complete</string>
    <string name="mailbox">Mailbox</string>
    <string name="info">Info</string>
    <!-- info plist keys need to pre prefixed with INFOPLIST., spaces need to be replaced with dots and dashes need to replaced with underscores -->
    <string name="INFOPLIST.Privacy._.Camera.Usage.Description">Allowing access to the camera lets you take photos and videos.</string>
    <string name="INFOPLIST.Privacy._.Contacts.Usage.Description">Allowing access to your address book lets you chat with contacts from your device.</string>
    <string name="INFOPLIST.Privacy.-.Microphone.Usage.Description">Allowing access to the microphone lets you record audio.</string>
    <string name="INFOPLIST.Privacy.-.Photo.Library.Usage.Description">Allowing access to the photo library allows you to upload images from it.</string>
</resources>
